pythoned/__init__.py
pythoned/__main__.py
pythoned-0.0.5.dist-info/METADATA
pythoned-0.0.5.dist-info/WHEEL
pythoned-0.0.5.dist-info/entry_points.txt
pythoned-0.0.5.dist-info/top_level.txt
pythoned-0.0.5.dist-info/RECORD
