Metadata-Version: 2.2
Name: pythoned
Version: 0.0.5
Summary: PYTHON EDitor: a command to edit lines using Python expressions
Home-page: http://github.com/ebonnal/pythoned
Author: ebonnal
Author-email: bonnal.enzo.dev@gmail.com
License: Apache 2.
Dynamic: author
Dynamic: author-email
Dynamic: description
Dynamic: description-content-type
Dynamic: home-page
Dynamic: license
Dynamic: summary
